{"skeleton":{"hash":"nZaUCiDmaZaxTOPO9WQSLKHPryg","spine":"3.8.95","x":-541,"y":-837.94,"width":1002.87,"height":1929.78,"images":"./enemy/enemy images/","audio":""},"bones":[{"name":"root"},{"name":"Torso","parent":"root","length":793.9,"rotation":89.75,"x":-8.42,"y":13.41},{"name":"Head","parent":"Torso","length":449.23,"rotation":-0.64,"x":654.11,"y":-40.97},{"name":"legRT","parent":"root","length":414.03,"rotation":-95.27,"x":-198.43,"y":70.35},{"name":"legLT","parent":"root","length":422.77,"rotation":-84.84,"x":136.39,"y":84.1},{"name":"legLB","parent":"legLT","length":508.78,"rotation":-5.49,"x":411.12,"y":1.05},{"name":"legRB","parent":"legRT","length":470.99,"rotation":3.49,"x":393.38,"y":1.03},{"name":"armRT","parent":"Torso","length":379.74,"rotation":173.62,"x":765.14,"y":245.95},{"name":"armRB","parent":"armRT","length":421.55,"rotation":3.84,"x":379.74},{"name":"armLT","parent":"Torso","length":405.89,"rotation":-173.55,"x":709.89,"y":-187.04},{"name":"armLB","parent":"armLT","length":362.48,"rotation":11.65,"x":405.89},{"name":"gun","parent":"armRB","length":283.96,"rotation":0.65,"x":428.56,"y":-2.61}],"slots":[{"name":"legLB","bone":"legLB","attachment":"legLB"},{"name":"legLT","bone":"legLT","attachment":"legLT"},{"name":"armLB","bone":"armLB","attachment":"armLB"},{"name":"armLT","bone":"armLT","attachment":"armLT"},{"name":"Torso","bone":"Torso","attachment":"Torso"},{"name":"legRB","bone":"legRB","attachment":"legRB"},{"name":"legRT","bone":"legRT","attachment":"legRT"},{"name":"Gun","bone":"gun","attachment":"Gun"},{"name":"Head","bone":"Head","attachment":"Head"},{"name":"armRB","bone":"armRB","attachment":"armRB"},{"name":"armRT","bone":"armRT","attachment":"armRT"}],"skins":[{"name":"default","attachments":{"Gun":{"Gun":{"x":208.01,"y":21.19,"scaleX":0.7706,"scaleY":0.7706,"rotation":-5,"width":1249,"height":371}},"Head":{"Head":{"x":216.98,"y":-29.68,"rotation":-89.11,"width":227,"height":416}},"Torso":{"Torso":{"x":415.83,"y":-12.8,"rotation":-89.75,"width":687,"height":863}},"armLB":{"armLB":{"x":256.59,"y":-6.57,"rotation":-15.19,"width":636,"height":256}},"armLT":{"armLT":{"x":187.96,"y":-16.56,"rotation":78.5,"width":227,"height":375}},"armRB":{"armRB":{"x":237.65,"y":-8.82,"rotation":-14.97,"width":631,"height":272}},"armRT":{"armRT":{"x":166.91,"y":22.19,"rotation":47.87,"width":280,"height":378}},"legLB":{"legLB":{"x":211.59,"y":86.18,"rotation":90.33,"width":405,"height":582}},"legLT":{"legLT":{"x":177.37,"y":-8.9,"rotation":84.84,"width":293,"height":476}},"legRB":{"legRB":{"x":196.79,"y":105.59,"rotation":95.41,"width":383,"height":610}},"legRT":{"legRT":{"x":137.4,"y":37.58,"rotation":89.58,"width":258,"height":482}}}}],"animations":{"idleAnim":{"bones":{"Torso":{"rotate":[{},{"time":0.5,"angle":-0.28},{"time":1}]},"legRB":{"rotate":[{},{"time":0.5,"angle":-3.52},{"time":1}]},"legRT":{"rotate":[{},{"time":0.5,"angle":1.36},{"time":1}]},"legLB":{"rotate":[{},{"time":0.5,"angle":-0.28},{"time":1}]},"legLT":{"rotate":[{},{"time":0.5,"angle":-0.28},{"time":1}]},"gun":{"rotate":[{},{"time":0.5,"angle":-0.28},{"time":1}]},"armRB":{"rotate":[{},{"time":0.5,"angle":4.05},{"time":1}]},"armRT":{"rotate":[{},{"time":0.5,"angle":-0.28},{"time":1}]},"armLB":{"rotate":[{},{"time":0.5,"angle":4.32},{"time":1}]},"armLT":{"rotate":[{},{"time":0.5,"angle":-0.28},{"time":1}]},"Head":{"rotate":[{},{"time":0.5,"angle":-1.41},{"time":1}]}}},"shootAnim":{"bones":{"armRT":{"rotate":[{"angle":43.48}]},"armRB":{"rotate":[{"angle":52.01},{"time":0.0667,"angle":55.79},{"time":0.1333,"angle":52.01}]},"gun":{"rotate":[{},{"time":0.0667,"angle":15.87},{"time":0.1333}]},"armLB":{"rotate":[{"angle":82.4}]},"armLT":{"rotate":[{"angle":20.39},{"time":0.0667,"angle":30.16},{"time":0.1333,"angle":20.39}]},"legLT":{"rotate":[{"angle":6.34},{"time":0.0667,"angle":9.04},{"time":0.1333,"angle":6.34}]},"legLB":{"rotate":[{"angle":-3.78},{"time":0.0667,"angle":-4.44},{"time":0.1333,"angle":-3.78}]},"legRT":{"rotate":[{"angle":0.15},{"time":0.0667,"angle":1.21},{"time":0.1333,"angle":0.15}]},"legRB":{"rotate":[{"angle":-8.45}]},"Torso":{"rotate":[{},{"time":0.0667,"angle":0.57},{"time":0.1333}]},"Head":{"rotate":[{"angle":-0.11},{"time":0.0667,"angle":3.97},{"time":0.1333,"angle":-0.11}]}}},"toShootAnim":{"bones":{"legLB":{"rotate":[{},{"time":0.1667,"angle":-3.78}]},"legRB":{"rotate":[{},{"time":0.1667,"angle":-8.45}]},"armLB":{"rotate":[{},{"time":0.1667,"angle":82.4}]},"legLT":{"rotate":[{},{"time":0.1667,"angle":6.34}]},"armRB":{"rotate":[{},{"time":0.1667,"angle":52.01}]},"armLT":{"rotate":[{},{"time":0.1667,"angle":20.39}]},"legRT":{"rotate":[{},{"time":0.1667,"angle":0.15}]},"armRT":{"rotate":[{},{"time":0.1667,"angle":43.48}]},"Torso":{"rotate":[{},{"time":0.1,"angle":0.88},{"time":0.1667}]},"Head":{"rotate":[{},{"time":0.1667,"angle":-0.11}]}}}}}